jpaddressparser/__init__.py
jpaddressparser/download.py
jpaddressparser/utils.py
jpaddressparser/version.py
jpaddressparser-0.1.0.dist-info/LICENSE
jpaddressparser-0.1.0.dist-info/WHEEL
jpaddressparser-0.1.0.dist-info/METADATA
jpaddressparser-0.1.0.dist-info/RECORD
